setup.py
smapp_collection_stats/__init__.py
smapp_collection_stats/backfill_keyword_stats.py
smapp_collection_stats/ensure_time_indexing.py
smapp_collection_stats/gen_keyword_stats.py
smapp_collection_stats.egg-info/PKG-INFO
smapp_collection_stats.egg-info/SOURCES.txt
smapp_collection_stats.egg-info/dependency_links.txt
smapp_collection_stats.egg-info/requires.txt
smapp_collection_stats.egg-info/top_level.txt