Metadata-Version: 1.0
Name: smapp-collection-stats
Version: 0.1.1
Summary: NYU SMaPP lab utility library
Home-page: http://smapp.nyu.edu
Author: NYU SMaPP
Author-email: smapp_programmer-group@nyu.edu
License: GPLv2
Platform: UNKNOWN
